LICENSE
mariner/__init__.py
mariner/__version__.py
mariner/commands/__init__.py
mariner/commands/config.py
mariner/commands/details.py
mariner/commands/download.py
mariner/commands/magnet.py
mariner/commands/open.py
mariner/commands/search.py
mariner/config/config.yaml
mariner/config.py
mariner/downloader.py
mariner/exceptions.py
mariner/main.py
mariner/mixins.py
mariner/proxies/__init__.py
mariner/proxies/piratebay.py
mariner/proxyplugin.py
mariner/searchengine.py
mariner/torrent.py
mariner/trackerplugin.py
mariner/trackers/__init__.py
mariner/trackers/anidex.disabled
mariner/trackers/archive.py
mariner/trackers/distrowatch.py
mariner/trackers/etree.py
mariner/trackers/kickasstorrents.disabled
mariner/trackers/limetorrents.py
mariner/trackers/linuxtracker.py
mariner/trackers/nyaa.py
mariner/trackers/nyaapantsu.py
mariner/trackers/piratebay.disabled
mariner/trackers/tokyotosho.py
mariner/trackers/torrentkitty.disabled
mariner/utils/__init__.py
mariner/utils/color.py
mariner/utils/parse.py
mariner/utils/path.py
mariner-1.5.1.dist-info/entry_points.txt
mariner-1.5.1.dist-info/LICENSE
mariner-1.5.1.dist-info/WHEEL
mariner-1.5.1.dist-info/METADATA
mariner-1.5.1.dist-info/RECORD
