Metadata-Version: 2.1
Name: mariner
Version: 1.5.1
Summary: Navigate torrents in CLI
Home-page: https://radek-sprta.gitlab.io/mariner/
License: GPL-3.0
Keywords: cli,torrent,search,scraper,downloader
Author: Radek Sprta
Author-email: mail@radeksprta.eu
Requires-Python: >=3.6,<4.0
Classifier: Development Status :: 5 - Production/Stable
Classifier: Environment :: Console
Classifier: Intended Audience :: End Users/Desktop
Classifier: License :: OSI Approved :: GNU General Public License v3 (GPLv3)
Classifier: Natural Language :: English
Classifier: Operating System :: Microsoft :: Windows
Classifier: Operating System :: POSIX :: Linux
Classifier: Programming Language :: Python :: 3
Classifier: Programming Language :: Python :: 3.6
Classifier: Programming Language :: Python :: 3.7
Classifier: Programming Language :: Python :: 3.8
Classifier: Programming Language :: Python :: 3.9
Classifier: Topic :: Internet :: WWW/HTTP :: Indexing/Search
Requires-Dist: aiodns (>=2.0,<3.0)
Requires-Dist: aiofiles (>=0.6,<0.7)
Requires-Dist: aiohttp (>=3.7,<4.0)
Requires-Dist: beautifulsoup4 (>=4.9,<5.0)
Requires-Dist: cachalot (>=1.5,<2.0)
Requires-Dist: cliff (>=3.6,<4.0)
Requires-Dist: colorama (>=0.4,<0.5)
Requires-Dist: lxml (>=4.6,<5.0)
Requires-Dist: maya (>=0.6,<0.7)
Requires-Dist: ruamel.yaml (>=0.16,<0.17)
Requires-Dist: tokenize-rt (>=3.2,<4.0)
Project-URL: Documentation, https://radek-sprta.gitlab.io/mariner/
Project-URL: Repository, https://gitlab.com/radek-sprta/mariner
